{
  "id":  "a4d209bb-c1bf-4087-bd62-a671f35d4186",
  "brand":  "Lenovo",
  "name":  "Thinkpad P1",
  "cpu":  {
    "brand":  "Intel",
    "name":  "Core i7-9750H",
    "number_cores":  6,
    "number_threads":  11,
    "min_ghz":  2.234521488447838,
    "max_ghz":  4.13022255077245
  },
  "ram":  {
    "value":  "15",
    "unit":  "GIGABYTE"
  },
  "gpus":  [
    {
      "brand":  "AMD",
      "name":  "RX 5700-XT",
      "min_ghz":  1.369516615814131,
      "max_ghz":  1.4066093161352373,
      "memory":  {
        "value":  "5",
        "unit":  "GIGABYTE"
      }
    }
  ],
  "storages":  [
    {
      "driver":  "SSD",
      "memory":  {
        "value":  "498",
        "unit":  "GIGABYTE"
      }
    },
    {
      "driver":  "HDD",
      "memory":  {
        "value":  "6",
        "unit":  "TERABYTE"
      }
    }
  ],
  "screen":  {
    "size_inch":  14.357717,
    "resolution":  {
      "width":  5025,
      "height":  2827
    },
    "panel":  "OLED",
    "multitouch":  true
  },
  "keyboard":  {
    "layout":  "QWERTY",
    "backlit":  false
  },
  "weight_kg":  2.1970038796407656,
  "price_usd":  1594.997273049376,
  "release_year":  2019,
  "updated_at":  "2022-07-05T19:16:18.014077745Z"
}